{
  "annotations": {
    "list": [
      {
        "builtIn": 1,
        "datasource": {
          "type": "grafana",
          "uid": "-- Grafana --"
        },
        "enable": true,
        "hide": true,
        "iconColor": "rgba(0, 211, 255, 1)",
        "name": "Annotations & Alerts",
        "type": "dashboard"
      }
    ]
  },
  "editable": true,
  "fiscalYearStartMonth": 0,
  "graphTooltip": 1,
  "id": 0,
  "links": [],
  "panels": [
    {
      "collapsed": false,
      "gridPos": {
        "h": 1,
        "w": 24,
        "x": 0,
        "y": 0
      },
      "id": 1,
      "panels": [],
      "repeat": "node",
      "title": "$node",
      "type": "row"
    },
    {
      "datasource": {
        "default": false,
        "type": "prometheus",
        "uid": "prometheus"
      },
      "description": "CPU time spent busy vs idle, split by activity type",
      "fieldConfig": {
        "defaults": {
          "color": {
            "mode": "palette-classic"
          },
          "custom": {
            "axisBorderShow": false,
            "axisCenteredZero": false,
            "axisColorMode": "text",
            "axisLabel": "",
            "axisPlacement": "auto",
            "barAlignment": 0,
            "barWidthFactor": 0.6,
            "drawStyle": "line",
            "fillOpacity": 40,
            "gradientMode": "none",
            "hideFrom": {
              "legend": false,
              "tooltip": false,
              "viz": false
            },
            "insertNulls": false,
            "lineInterpolation": "smooth",
            "lineWidth": 1,
            "pointSize": 5,
            "scaleDistribution": {
              "type": "linear"
            },
            "showPoints": "never",
            "showValues": false,
            "spanNulls": false,
            "stacking": {
              "group": "A",
              "mode": "normal"
            },
            "thresholdsStyle": {
              "mode": "off"
            }
          },
          "links": [],
          "mappings": [],
          "min": 0,
          "thresholds": {
            "mode": "absolute",
            "steps": [
              {
                "color": "green",
                "value": 0
              }
            ]
          }
        },
        "overrides": [
          {
            "matcher": {
              "id": "byName",
              "options": "Busy Iowait"
            },
            "properties": [
              {
                "id": "color",
                "value": {
                  "fixedColor": "#890F02",
                  "mode": "fixed"
                }
              }
            ]
          },
          {
            "matcher": {
              "id": "byName",
              "options": "Idle"
            },
            "properties": [
              {
                "id": "color",
                "value": {
                  "fixedColor": "#052B51",
                  "mode": "fixed"
                }
              }
            ]
          },
          {
            "matcher": {
              "id": "byName",
              "options": "Busy System"
            },
            "properties": [
              {
                "id": "color",
                "value": {
                  "fixedColor": "#EAB839",
                  "mode": "fixed"
                }
              }
            ]
          },
          {
            "matcher": {
              "id": "byName",
              "options": "Busy User"
            },
            "properties": [
              {
                "id": "color",
                "value": {
                  "fixedColor": "#0A437C",
                  "mode": "fixed"
                }
              }
            ]
          },
          {
            "matcher": {
              "id": "byName",
              "options": "Busy Other"
            },
            "properties": [
              {
                "id": "color",
                "value": {
                  "fixedColor": "#6D1F62",
                  "mode": "fixed"
                }
              }
            ]
          },
          {
            "matcher": {
              "id": "byName",
              "options": "Allocatable"
            },
            "properties": [
              {
                "id": "custom.fillOpacity",
                "value": 0
              },
              {
                "id": "color",
                "value": {
                  "fixedColor": "red",
                  "mode": "fixed"
                }
              },
              {
                "id": "custom.lineStyle",
                "value": {
                  "dash": [
                    10,
                    10
                  ],
                  "fill": "dash"
                }
              },
              {
                "id": "custom.stacking",
                "value": {
                  "group": "A",
                  "mode": "none"
                }
              },
              {
                "id": "custom.lineWidth",
                "value": 2
              }
            ]
          },
          {
            "matcher": {
              "id": "byName",
              "options": "Requests"
            },
            "properties": [
              {
                "id": "color",
                "value": {
                  "fixedColor": "yellow",
                  "mode": "fixed"
                }
              },
              {
                "id": "custom.fillOpacity",
                "value": 0
              },
              {
                "id": "custom.lineStyle",
                "value": {
                  "dash": [
                    10,
                    10
                  ],
                  "fill": "dash"
                }
              },
              {
                "id": "custom.stacking",
                "value": {
                  "group": "A",
                  "mode": "none"
                }
              },
              {
                "id": "custom.lineWidth",
                "value": 2
              }
            ]
          },
          {
            "matcher": {
              "id": "byName",
              "options": "Limits"
            },
            "properties": [
              {
                "id": "color",
                "value": {
                  "fixedColor": "orange",
                  "mode": "fixed"
                }
              },
              {
                "id": "custom.fillOpacity",
                "value": 0
              },
              {
                "id": "custom.lineStyle",
                "value": {
                  "dash": [
                    10,
                    10
                  ],
                  "fill": "dash"
                }
              },
              {
                "id": "custom.stacking",
                "value": {
                  "group": "A",
                  "mode": "none"
                }
              },
              {
                "id": "custom.lineWidth",
                "value": 2
              }
            ]
          }
        ]
      },
      "gridPos": {
        "h": 6,
        "w": 12,
        "x": 0,
        "y": 1
      },
      "id": 3,
      "options": {
        "legend": {
          "calcs": [],
          "displayMode": "list",
          "placement": "bottom",
          "showLegend": false,
          "width": 250
        },
        "tooltip": {
          "hideZeros": false,
          "mode": "multi",
          "sort": "desc"
        }
      },
      "pluginVersion": "12.3.0-18578466485",
      "targets": [
        {
          "datasource": {
            "type": "prometheus",
            "uid": "prometheus"
          },
          "editorMode": "code",
          "exemplar": false,
          "expr": "sum by(instance) (\r\n  irate(node_cpu_seconds_total{job=\"$job\", mode=\"system\"}[$__rate_interval])\r\n)\r\n*\r\non(instance) group_left(nodename)\r\nmax by(instance,nodename) (node_uname_info{job=\"$job\", nodename=\"$node\"})",
          "format": "time_series",
          "hide": false,
          "instant": false,
          "intervalFactor": 1,
          "legendFormat": "Busy System",
          "range": true,
          "refId": "A",
          "step": 240
        },
        {
          "datasource": {
            "type": "prometheus",
            "uid": "prometheus"
          },
          "editorMode": "code",
          "expr": "sum by(instance)(\r\n  irate(node_cpu_seconds_total{job=\"$job\", mode=\"user\"}[$__rate_interval])\r\n)\r\n*\r\non(instance) group_left(nodename)\r\nmax by(instance,nodename)(node_uname_info{job=\"$job\", nodename=\"$node\"})",
          "format": "time_series",
          "hide": false,
          "intervalFactor": 1,
          "legendFormat": "Busy User",
          "range": true,
          "refId": "B",
          "step": 240
        },
        {
          "datasource": {
            "type": "prometheus",
            "uid": "prometheus"
          },
          "editorMode": "code",
          "expr": "sum by(instance)(\r\n  irate(node_cpu_seconds_total{job=\"$job\", mode=\"iowait\"}[$__rate_interval])\r\n)\r\n* on(instance) group_left(nodename)\r\nmax by(instance,nodename)(node_uname_info{job=\"$job\", nodename=\"$node\"})",
          "format": "time_series",
          "hide": false,
          "intervalFactor": 1,
          "legendFormat": "Busy Iowait",
          "range": true,
          "refId": "C",
          "step": 240
        },
        {
          "datasource": {
            "type": "prometheus",
            "uid": "prometheus"
          },
          "editorMode": "code",
          "expr": "sum by(instance)(\r\n  irate(node_cpu_seconds_total{job=\"$job\", mode=~\".*irq\"}[$__rate_interval])\r\n)\r\n* on(instance) group_left(nodename)\r\nmax by(instance,nodename)(node_uname_info{job=\"$job\", nodename=\"$node\"})",
          "format": "time_series",
          "hide": false,
          "intervalFactor": 1,
          "legendFormat": "Busy IRQs",
          "range": true,
          "refId": "D",
          "step": 240
        },
        {
          "datasource": {
            "type": "prometheus",
            "uid": "prometheus"
          },
          "editorMode": "code",
          "expr": "sum by(instance)(\r\n  irate(node_cpu_seconds_total{job=\"$job\",\r\n                               mode!=\"idle\",\r\n                               mode!=\"user\",\r\n                               mode!=\"system\",\r\n                               mode!=\"iowait\",\r\n                               mode!=\"irq\",\r\n                               mode!=\"softirq\"}[$__rate_interval])\r\n)\r\n* on(instance) group_left(nodename)\r\nmax by(instance,nodename)(node_uname_info{job=\"$job\", nodename=\"$node\"})",
          "format": "time_series",
          "hide": false,
          "intervalFactor": 1,
          "legendFormat": "Busy Other",
          "range": true,
          "refId": "E",
          "step": 240
        },
        {
          "datasource": {
            "type": "prometheus",
            "uid": "prometheus"
          },
          "editorMode": "code",
          "expr": "sum by(instance)(\r\n  irate(node_cpu_seconds_total{job=\"$job\", mode=\"idle\"}[$__rate_interval])\r\n)\r\n* on(instance) group_left(nodename)\r\nmax by(instance,nodename)(node_uname_info{job=\"$job\", nodename=\"$node\"})",
          "format": "time_series",
          "hide": false,
          "intervalFactor": 1,
          "legendFormat": "Idle",
          "range": true,
          "refId": "F",
          "step": 240
        },
        {
          "datasource": {
            "type": "prometheus",
            "uid": "prometheus"
          },
          "editorMode": "code",
          "expr": "sum(kube_node_status_allocatable{resource=\"cpu\", unit=\"core\",node=\"$node\"}) by (instance)",
          "hide": false,
          "instant": false,
          "legendFormat": "Allocatable",
          "range": true,
          "refId": "G"
        },
        {
          "datasource": {
            "type": "prometheus",
            "uid": "prometheus"
          },
          "editorMode": "code",
          "expr": "sum by(node)(\r\n  kube_pod_container_resource_requests{resource=\"cpu\",unit=\"core\",node=\"$node\"}\r\n)",
          "hide": false,
          "instant": false,
          "legendFormat": "Requests",
          "range": true,
          "refId": "H"
        },
        {
          "datasource": {
            "type": "prometheus",
            "uid": "prometheus"
          },
          "editorMode": "code",
          "expr": "sum by(node)(\r\n  kube_pod_container_resource_limits{resource=\"cpu\",unit=\"core\",node=\"$node\"}\r\n)",
          "hide": false,
          "instant": false,
          "legendFormat": "Limits",
          "range": true,
          "refId": "I"
        }
      ],
      "title": "CPU Basic",
      "type": "timeseries"
    },
    {
      "datasource": {
        "default": false,
        "type": "prometheus",
        "uid": "prometheus"
      },
      "description": "RAM and swap usage overview, including caches",
      "fieldConfig": {
        "defaults": {
          "color": {
            "mode": "palette-classic"
          },
          "custom": {
            "axisBorderShow": false,
            "axisCenteredZero": false,
            "axisColorMode": "text",
            "axisLabel": "",
            "axisPlacement": "auto",
            "barAlignment": 0,
            "barWidthFactor": 0.6,
            "drawStyle": "line",
            "fillOpacity": 40,
            "gradientMode": "none",
            "hideFrom": {
              "legend": false,
              "tooltip": false,
              "viz": false
            },
            "insertNulls": false,
            "lineInterpolation": "linear",
            "lineWidth": 1,
            "pointSize": 5,
            "scaleDistribution": {
              "type": "linear"
            },
            "showPoints": "never",
            "showValues": false,
            "spanNulls": false,
            "stacking": {
              "group": "A",
              "mode": "normal"
            },
            "thresholdsStyle": {
              "mode": "off"
            }
          },
          "links": [],
          "mappings": [],
          "min": 0,
          "thresholds": {
            "mode": "absolute",
            "steps": [
              {
                "color": "green",
                "value": 0
              }
            ]
          },
          "unit": "bytes"
        },
        "overrides": [
          {
            "matcher": {
              "id": "byName",
              "options": "Swap used"
            },
            "properties": [
              {
                "id": "color",
                "value": {
                  "fixedColor": "#BF1B00",
                  "mode": "fixed"
                }
              }
            ]
          },
          {
            "matcher": {
              "id": "byName",
              "options": "Total"
            },
            "properties": [
              {
                "id": "color",
                "value": {
                  "fixedColor": "#E0F9D7",
                  "mode": "fixed"
                }
              },
              {
                "id": "custom.fillOpacity",
                "value": 0
              },
              {
                "id": "custom.stacking",
                "value": {
                  "group": false,
                  "mode": "normal"
                }
              }
            ]
          },
          {
            "matcher": {
              "id": "byName",
              "options": "Cache + Buffer"
            },
            "properties": [
              {
                "id": "color",
                "value": {
                  "fixedColor": "#052B51",
                  "mode": "fixed"
                }
              }
            ]
          },
          {
            "matcher": {
              "id": "byName",
              "options": "Free"
            },
            "properties": [
              {
                "id": "color",
                "value": {
                  "fixedColor": "#7EB26D",
                  "mode": "fixed"
                }
              }
            ]
          },
          {
            "matcher": {
              "id": "byName",
              "options": "Allocatable"
            },
            "properties": [
              {
                "id": "custom.fillOpacity",
                "value": 0
              },
              {
                "id": "custom.stacking",
                "value": {
                  "group": "A",
                  "mode": "none"
                }
              },
              {
                "id": "custom.lineStyle",
                "value": {
                  "dash": [
                    10,
                    10
                  ],
                  "fill": "dash"
                }
              },
              {
                "id": "color",
                "value": {
                  "fixedColor": "red",
                  "mode": "fixed"
                }
              },
              {
                "id": "custom.lineWidth",
                "value": 2
              }
            ]
          },
          {
            "matcher": {
              "id": "byName",
              "options": "Requests"
            },
            "properties": [
              {
                "id": "custom.stacking",
                "value": {
                  "group": "A",
                  "mode": "none"
                }
              },
              {
                "id": "custom.lineStyle",
                "value": {
                  "dash": [
                    10,
                    10
                  ],
                  "fill": "dash"
                }
              },
              {
                "id": "color",
                "value": {
                  "fixedColor": "yellow",
                  "mode": "fixed"
                }
              },
              {
                "id": "custom.fillOpacity",
                "value": 0
              },
              {
                "id": "custom.lineWidth",
                "value": 2
              }
            ]
          },
          {
            "matcher": {
              "id": "byName",
              "options": "Limits"
            },
            "properties": [
              {
                "id": "custom.stacking",
                "value": {
                  "group": "A",
                  "mode": "none"
                }
              },
              {
                "id": "custom.fillOpacity",
                "value": 0
              },
              {
                "id": "color",
                "value": {
                  "fixedColor": "orange",
                  "mode": "fixed"
                }
              },
              {
                "id": "custom.lineStyle",
                "value": {
                  "dash": [
                    10,
                    10
                  ],
                  "fill": "dash"
                }
              },
              {
                "id": "custom.lineWidth",
                "value": 2
              }
            ]
          }
        ]
      },
      "gridPos": {
        "h": 6,
        "w": 12,
        "x": 12,
        "y": 1
      },
      "id": 28,
      "options": {
        "legend": {
          "calcs": [],
          "displayMode": "list",
          "placement": "bottom",
          "showLegend": false,
          "width": 350
        },
        "tooltip": {
          "hideZeros": false,
          "mode": "multi",
          "sort": "none"
        }
      },
      "pluginVersion": "12.3.0-18578466485",
      "targets": [
        {
          "datasource": {
            "type": "prometheus",
            "uid": "prometheus"
          },
          "editorMode": "code",
          "expr": "max by (instance) (node_memory_MemTotal_bytes{job=\"$job\"})\r\n*\r\non(instance) group_left(nodename)\r\nmax by (instance,nodename) (node_uname_info{job=\"$job\",nodename=\"$node\"})",
          "format": "time_series",
          "hide": false,
          "intervalFactor": 1,
          "legendFormat": "Total",
          "range": true,
          "refId": "A",
          "step": 240
        },
        {
          "datasource": {
            "type": "prometheus",
            "uid": "prometheus"
          },
          "editorMode": "code",
          "expr": "max by (instance) (\r\n  node_memory_MemTotal_bytes{job=\"$job\"} \r\n  - node_memory_MemFree_bytes{job=\"$job\"} \r\n  - (node_memory_Cached_bytes{job=\"$job\"} \r\n  + node_memory_Buffers_bytes{job=\"$job\"} + node_memory_SReclaimable_bytes{job=\"$job\"})\r\n)\r\n*\r\non(instance) group_left(nodename)\r\nmax by (instance,nodename) (node_uname_info{job=\"$job\",nodename=\"$node\"})",
          "format": "time_series",
          "hide": false,
          "intervalFactor": 1,
          "legendFormat": "Used",
          "range": true,
          "refId": "B",
          "step": 240
        },
        {
          "datasource": {
            "type": "prometheus",
            "uid": "prometheus"
          },
          "editorMode": "code",
          "expr": "max by (instance) (  \r\n  node_memory_Cached_bytes{job=\"$job\"} \r\n  + node_memory_Buffers_bytes{job=\"$job\"} \r\n  + node_memory_SReclaimable_bytes{job=\"$job\"}\r\n)\r\n*\r\non(instance) group_left(nodename)\r\nmax by (instance,nodename) (node_uname_info{job=\"$job\",nodename=\"$node\"})",
          "format": "time_series",
          "intervalFactor": 1,
          "legendFormat": "Cache + Buffer",
          "range": true,
          "refId": "C",
          "step": 240
        },
        {
          "datasource": {
            "type": "prometheus",
            "uid": "prometheus"
          },
          "editorMode": "code",
          "expr": "max by (instance) (node_memory_MemFree_bytes{job=\"$job\"})\r\n*\r\non(instance) group_left(nodename)\r\nmax by (instance,nodename) (node_uname_info{job=\"$job\",nodename=\"$node\"})",
          "format": "time_series",
          "intervalFactor": 1,
          "legendFormat": "Free",
          "range": true,
          "refId": "D",
          "step": 240
        },
        {
          "datasource": {
            "type": "prometheus",
            "uid": "prometheus"
          },
          "editorMode": "code",
          "expr": "max by (instance) (\r\n  (node_memory_SwapTotal_bytes{job=\"$job\"} \r\n  - node_memory_SwapFree_bytes{job=\"$job\"})\r\n)\r\n*\r\non(instance) group_left(nodename)\r\nmax by (instance,nodename) (node_uname_info{job=\"$job\",nodename=\"$node\"})",
          "format": "time_series",
          "intervalFactor": 1,
          "legendFormat": "Swap used",
          "range": true,
          "refId": "E",
          "step": 240
        },
        {
          "datasource": {
            "type": "prometheus",
            "uid": "prometheus"
          },
          "editorMode": "code",
          "expr": "sum(kube_node_status_allocatable{resource=\"memory\",unit=\"byte\",node=\"$node\"}) by (instance)",
          "hide": false,
          "instant": false,
          "legendFormat": "Allocatable",
          "range": true,
          "refId": "F"
        },
        {
          "datasource": {
            "type": "prometheus",
            "uid": "prometheus"
          },
          "editorMode": "code",
          "expr": "sum by(node)(\r\n  kube_pod_container_resource_requests{resource=\"memory\",unit=\"byte\",node=\"$node\"}\r\n)",
          "hide": false,
          "instant": false,
          "legendFormat": "Requests",
          "range": true,
          "refId": "G"
        },
        {
          "datasource": {
            "type": "prometheus",
            "uid": "prometheus"
          },
          "editorMode": "code",
          "expr": "sum by(node)(\r\n  kube_pod_container_resource_limits{resource=\"memory\",unit=\"byte\",node=\"$node\"}\r\n)",
          "hide": false,
          "instant": false,
          "legendFormat": "Limits",
          "range": true,
          "refId": "H"
        }
      ],
      "title": "Memory Basic",
      "type": "timeseries"
    },
    {
      "datasource": {
        "default": false,
        "type": "datasource",
        "uid": "-- Mixed --"
      },
      "fieldConfig": {
        "defaults": {
          "custom": {
            "align": "auto",
            "cellOptions": {
              "type": "auto"
            },
            "footer": {
              "reducers": [
                "sum"
              ]
            },
            "inspect": false
          },
          "mappings": [
            {
              "options": {
                "1": {
                  "color": "green",
                  "index": 0,
                  "text": "Running"
                }
              },
              "type": "value"
            }
          ],
          "thresholds": {
            "mode": "absolute",
            "steps": [
              {
                "color": "green",
                "value": 0
              },
              {
                "color": "red",
                "value": 80
              }
            ]
          }
        },
        "overrides": [
          {
            "matcher": {
              "id": "byRegexp",
              "options": "/MEM.*/"
            },
            "properties": [
              {
                "id": "unit",
                "value": "bytes"
              }
            ]
          },
          {
            "matcher": {
              "id": "byName",
              "options": "Pod"
            },
            "properties": [
              {
                "id": "custom.width",
                "value": 323
              }
            ]
          },
          {
            "matcher": {
              "id": "byRegexp",
              "options": "/.*Requests/"
            },
            "properties": [
              {
                "id": "custom.minWidth",
                "value": 50
              }
            ]
          }
        ]
      },
      "gridPos": {
        "h": 6,
        "w": 24,
        "x": 0,
        "y": 7
      },
      "id": 27,
      "options": {
        "cellHeight": "sm",
        "showHeader": true,
        "sortBy": [
          {
            "desc": true,
            "displayName": "Namespace"
          }
        ]
      },
      "pluginVersion": "12.3.0-18578466485",
      "targets": [
        {
          "datasource": {
            "type": "prometheus",
            "uid": "${datasource}"
          },
          "editorMode": "code",
          "expr": "sum(node_namespace_pod_container:container_cpu_usage_seconds_total:sum_irate{cluster=\"$cluster\", node=~\"$node\"}) by (pod,namespace)",
          "format": "table",
          "hide": false,
          "instant": true,
          "refId": "A"
        },
        {
          "datasource": {
            "type": "prometheus",
            "uid": "${datasource}"
          },
          "expr": "sum(cluster:namespace:pod_cpu:active:kube_pod_container_resource_requests{cluster=\"$cluster\", node=~\"$node\"}) by (pod)",
          "format": "table",
          "hide": false,
          "instant": true,
          "refId": "B"
        },
        {
          "datasource": {
            "type": "prometheus",
            "uid": "${datasource}"
          },
          "expr": "sum(cluster:namespace:pod_cpu:active:kube_pod_container_resource_limits{cluster=\"$cluster\", node=~\"$node\"}) by (pod)",
          "format": "table",
          "hide": false,
          "instant": true,
          "refId": "D"
        },
        {
          "datasource": {
            "type": "prometheus",
            "uid": "${datasource}"
          },
          "editorMode": "code",
          "exemplar": false,
          "expr": "sum(cluster:namespace:pod_memory:active:kube_pod_container_resource_requests{cluster=\"$cluster\", node=~\"$node\"}) by (pod)",
          "format": "table",
          "hide": false,
          "instant": true,
          "legendFormat": "__auto",
          "range": false,
          "refId": "C"
        },
        {
          "datasource": {
            "type": "prometheus",
            "uid": "${datasource}"
          },
          "editorMode": "code",
          "exemplar": false,
          "expr": "sum(cluster:namespace:pod_memory:active:kube_pod_container_resource_limits{cluster=\"$cluster\", node=~\"$node\"}) by (pod)",
          "format": "table",
          "hide": false,
          "instant": true,
          "legendFormat": "__auto",
          "range": false,
          "refId": "E"
        },
        {
          "datasource": {
            "type": "prometheus",
            "uid": "${datasource}"
          },
          "editorMode": "code",
          "exemplar": false,
          "expr": "(\r\n  kube_pod_status_phase{phase=\"Running\"} == 1\r\n)\r\n* on(namespace,pod) group_left(node)\r\n  max by (namespace,pod,node) (kube_pod_info{node=~\"$node\"})\r\n",
          "format": "table",
          "hide": false,
          "instant": true,
          "legendFormat": "__auto",
          "range": false,
          "refId": "F"
        }
      ],
      "title": "CPU Quota",
      "transformations": [
        {
          "id": "joinByField",
          "options": {
            "byField": "pod",
            "mode": "outer"
          }
        },
        {
          "id": "organize",
          "options": {
            "excludeByName": {
              "Time": true,
              "Time 1": true,
              "Time 2": true,
              "Time 3": true,
              "Time 4": true,
              "Time 5": true,
              "Value": false,
              "Value #A": false,
              "Value #B": false,
              "Value #F": true,
              "cluster": true,
              "container": true,
              "endpoint": true,
              "instance": true,
              "job": true,
              "namespace": true,
              "node": true,
              "phase": true,
              "prometheus": true,
              "prometheus_replica": true,
              "service": true,
              "uid": true
            },
            "includeByName": {},
            "indexByName": {
              "Time 1": 1,
              "Time 2": 3,
              "Time 3": 5,
              "Time 4": 7,
              "Time 5": 9,
              "Value #A": 2,
              "Value #B": 4,
              "Value #C": 6,
              "Value #D": 8,
              "Value #E": 10,
              "namespace": 11,
              "pod": 0
            },
            "renameByName": {
              "Value": "Status",
              "Value #A": "CPU Usage",
              "Value #B": "CPU Requests",
              "Value #C": "MEM Requests",
              "Value #D": "CPU Limits",
              "Value #E": "MEM Limits",
              "Value #F": "Status",
              "namespace": "Namespace",
              "pod": "Pod"
            }
          }
        }
      ],
      "type": "table"
    }
  ],
  "preload": false,
  "refresh": "",
  "schemaVersion": 42,
  "tags": [],
  "templating": {
    "list": [
      {
        "current": {
          "text": "prometheus",
          "value": "prometheus"
        },
        "includeAll": false,
        "name": "datasource",
        "options": [],
        "query": "prometheus",
        "refresh": 1,
        "regex": "",
        "type": "datasource"
      },
      {
        "current": {
          "text": "node-exporter",
          "value": "node-exporter"
        },
        "datasource": {
          "type": "prometheus",
          "uid": "${datasource}"
        },
        "definition": "label_values(node_uname_info,job)",
        "includeAll": false,
        "name": "job",
        "options": [],
        "query": {
          "qryType": 1,
          "query": "label_values(node_uname_info,job)",
          "refId": "PrometheusVariableQueryEditor-VariableQuery"
        },
        "refresh": 1,
        "regex": "",
        "type": "query"
      },
      {
        "current": {
          "text": "infra",
          "value": "infra"
        },
        "datasource": {
          "type": "prometheus",
          "uid": "${datasource}"
        },
        "definition": "label_values(node_uname_info{job=\"$job\"},cluster)",
        "includeAll": false,
        "name": "cluster",
        "options": [],
        "query": {
          "qryType": 1,
          "query": "label_values(node_uname_info{job=\"$job\"},cluster)",
          "refId": "PrometheusVariableQueryEditor-VariableQuery"
        },
        "refresh": 1,
        "regex": "",
        "type": "query"
      },
      {
        "allValue": ".+",
        "allowCustomValue": false,
        "current": {
          "text": "All",
          "value": [
            "$__all"
          ]
        },
        "datasource": {
          "type": "prometheus",
          "uid": "${datasource}"
        },
        "definition": "label_values(node_uname_info{job=\"$job\"},instance)",
        "hide": 2,
        "includeAll": true,
        "multi": true,
        "name": "instance",
        "options": [],
        "query": {
          "qryType": 1,
          "query": "label_values(node_uname_info{job=\"$job\"},instance)",
          "refId": "PrometheusVariableQueryEditor-VariableQuery"
        },
        "refresh": 1,
        "regex": "",
        "type": "query"
      },
      {
        "allValue": ".+",
        "current": {
          "text": "All",
          "value": [
            "$__all"
          ]
        },
        "datasource": {
          "type": "prometheus",
          "uid": "${datasource}"
        },
        "definition": "label_values(node_uname_info{job=\"$job\", instance=~\"$instance\", cluster=\"$cluster\"},nodename)",
        "includeAll": true,
        "multi": true,
        "name": "node",
        "options": [],
        "query": {
          "qryType": 1,
          "query": "label_values(node_uname_info{job=\"$job\", instance=~\"$instance\", cluster=\"$cluster\"},nodename)",
          "refId": "PrometheusVariableQueryEditor-VariableQuery"
        },
        "refresh": 1,
        "regex": "",
        "type": "query"
      }
    ]
  },
  "time": {
    "from": "now-1h",
    "to": "now"
  },
  "timepicker": {},
  "timezone": "browser",
  "title": "node-exporter - kubernetes",
  "uid": "node-exporter_kuberetes",
  "version": 2
}